your_project_name/__init__.py
your_project_name-0.0.1.dist-info/LICENSE
your_project_name-0.0.1.dist-info/WHEEL
your_project_name-0.0.1.dist-info/METADATA
your_project_name-0.0.1.dist-info/RECORD
