Metadata-Version: 2.1
Name: your-project-name
Version: 0.0.1
Summary: Short description of your project
Home-page: https://darth-veitcher.github.io/your-project-name/latest
Author: James Veitch
Author-email: 1722315+darth-veitcher@users.noreply.github.com
Requires-Python: >=3.7,<4.0
Classifier: License :: OSI Approved :: MIT License
Classifier: Programming Language :: Python :: 3
Classifier: Programming Language :: Python :: 3.7
Classifier: Programming Language :: Python :: 3.8
Classifier: Programming Language :: Python :: 3.9
Classifier: Programming Language :: Python :: 3.10
Classifier: Programming Language :: Python :: 3.11
Classifier: Programming Language :: Python :: 3 :: Only
Classifier: Programming Language :: Python :: 3.10
Classifier: Programming Language :: Python :: 3.7
Classifier: Programming Language :: Python :: 3.8
Classifier: Programming Language :: Python :: 3.9
Classifier: Topic :: Software Development :: Libraries :: Python Modules
Requires-Dist: importlib-metadata (>=4,<5); python_version < "3.8"
Project-URL: Documentation, https://darth-veitcher.github.io/your-project-name/latest
Project-URL: Repository, https://github.com/darth-veitcher/your-project-name
